{"0": "(ROOT: (S: (NP: (NNP: 'Caecina')) (VP: (VBN: 'mocked') (PP: (IN: 'at') (NP: (NP: (NNP: 'Valens')) (PP: (IN: 'for') (NP: (PRP$: 'his') (ADJP: (JJ: 'dirty') (CC: 'and') (JJ: 'dishonest')) (NNS: 'ways282'))))))))", "1": "(ROOT: (FRAG: (NP: (CD: '80'))))", "2": "(ROOT: (S: (NP: (NP: (DT: 'The') (NNS: 'tribunes') (CC: 'and') (NNS: 'centurions')) (CC: 'and') (NP: (DT: 'the') (JJ: 'common') (NNS: 'soldiers'))) (VP: (VBD: 'were') (VP: (VBN: 'attracted') (NP: (DT: 'each')) (PP: (VBG: 'according') (PP: (TO: 'to') (NP: (PRP$: 'his') (NN: 'character')))) (PP: (CC: 'either') (PP: (IN: 'by') (NP: (NNP: 'Titus') (JJ: 'meritorious') (NN: 'industry'))) (CC: 'or') (PP: (IN: 'by') (NP: (NP: (PRP$: 'his') (JJ: 'gay') (NN: 'indulgence')) (PP: (IN: 'in') (NP: (NN: 'pleasure'))))))))))", "3": "(ROOT: (S: (NP: (PRP: 'It')) (VP: (VBZ: 'is') (PP: (TO: 'to') (NP: (PRP: 'him'))) (SBAR: (IN: 'that') (S: (NP: (NNP: 'Romes') (NN: 'attention')) (VP: (VBZ: 'turns') (SBAR: (IN: 'while') (S: (NP: (PRP: 'you')) (VP: (VBP: 'Sire') (ADJP: (JJ: 'careless') (SBAR: (WHNP: (WP: 'who')) (S: (VP: (VBZ: 'is') (NP: (NP: (NN: 'friend') (CC: 'or') (NN: 'foe') (NN: 'cherish')) (PP: (IN: 'in') (NP: (NP: (PRP$: 'your') (NN: 'bosom')) (NP: (DT: 'a') (NN: 'rival')))) (SBAR: (WHNP: (WP: 'who')) (S: (VP: (VP: (VBZ: 'sits') (S: (VP: (VBG: 'feasting') (PP: (IN: 'at') (NP: (PRP$: 'his') (NN: 'table')))))) (CC: 'and') (VP: (VBZ: 'watches') (NP: (PRP$: 'his') (NN: 'emperor')) (PP: (IN: 'in') (NP: (NN: 'pain')))))))))))))))))))))", "4": "(ROOT: (S: (CC: 'But') (NP: (DT: 'the') (JJS: 'heaviest') (NN: 'burden')) (VP: (VBD: 'was') (NP: (NP: (DT: 'the') (NN: 'raising')) (PP: (IN: 'of') (NP: (NN: 'money')))))))", "5": "(ROOT: (SBAR: (WHADVP: (WRB: 'When')) (S: (NP: (NP: (DT: 'all') (NN: 'fear')) (PP: (IN: 'of') (NP: (NN: 'violence')))) (VP: (VBD: 'was') (PP: (IN: 'at') (NP: (NP: (DT: 'an') (NN: 'end')) (SBAR: (S: (NP: (NNP: 'Domitian')) (VP: (VP: (VBD: 'came') (NP: (NNS: 'out227'))) (CC: 'and') (VP: (VBD: 'presented') (NP: (PRP: 'himself')) (PP: (TO: 'to') (NP: (NP: (DT: 'the') (NNS: 'generals')) (PP: (IN: 'of') (NP: (PRP$: 'his') (NN: 'party')))))))))))))))", "6": "(ROOT: (FRAG: (NP: (DT: 'All') (NN: 'night') (SBAR: (S: (NP: (NP: (DT: 'the') (NN: 'battle')) (VP: (VBN: 'raged') (PP: (IN: 'with') (NP: (VBG: 'varying') (NN: 'fortune'))))) (ADVP: (RB: 'never')) (VP: (VBD: 'decided') (RB: 'always') (VP: (ADVP: (RB: 'savagely')) (JJ: 'contested'))))))))", "7": "(ROOT: (S: (NP: (DT: 'The') (NNPS: 'Vitellians')) (VP: (VBD: 'provided') (NP: (JJ: 'mantlets') (NNS: 'fascines') (CC: 'and') (NNS: 'penthouses258')) (S: (VP: (TO: 'to') (VP: (VB: 'protect') (NP: (DT: 'the') (NNS: 'assailants')) (SBAR: (IN: 'while') (S: (S: (VP: (VBG: 'undermining') (S: (NP: (DT: 'the') (NNS: 'walls')) (NP: (DT: 'the') (NNPS: 'Othonians'))))) (VP: (VBD: 'procured') (NP: (NP: (NNS: 'stakes')) (CC: 'and') (NP: (NP: (JJ: 'huge') (NNS: 'masses')) (PP: (IN: 'of') (NP: (NN: 'stone') (CC: 'or') (NN: 'lead') (CC: 'or') (NN: 'brass'))))) (S: (VP: (TO: 'to') (VP: (VP: (VB: 'break') (PP: (IN: 'through') (NP: (DT: 'the') (JJ: 'enemys') (NN: 'formation')))) (CC: 'and') (VP: (VB: 'crush') (NP: (PRP: 'them')) (PP: (TO: 'to') (NP: (NNS: 'pieces'))))))))))))))))", "8": "(ROOT: (S: (VP: (VB: '335') (SBAR: (S: (PP: (IN: 'From') (NP: (DT: 'this') (NN: 'phrase'))) (NP: (PRP: 'it')) (VP: (VBZ: 'is') (RB: 'not') (ADJP: (JJ: 'clear')) (SBAR: (IN: 'whether') (S: (NP: (NP: (DT: 'the') (JJ: 'actual') (NN: 'news')) (PP: (IN: 'of') (NP: (PRP$: 'his') (NN: 'suicide')))) (VP: (VBD: 'had') (VP: (VBN: 'arrived')))))))))))", "9": "(ROOT: (SBAR: (WHADVP: (WRB: 'When')) (S: (NP: (NP: (DT: 'the') (NN: 'news')) (PP: (IN: 'of') (NP: (DT: 'this')))) (VP: (VBD: 'reached') (NP: (NP: (NNP: 'Rome') (NNP: 'Marcus') (NNP: 'Aponius')) (SBAR: (S: (NP: (NP: (DT: 'the') (NN: 'governor')) (PP: (IN: 'of') (NP: (NNP: 'Moesia')))) (VP: (VBD: 'was') (VP: (VBN: 'granted') (NP: (DT: 'a') (JJ: 'triumphal') (NN: 'statue177')) (SBAR: (IN: 'while') (S: (NP: (NP: (DT: 'the') (JJ: 'commanding') (NNS: 'officers')) (PP: (IN: 'of') (NP: (DT: 'the') (NNP: 'legions') (NNP: 'Fulvius') (NNP: 'Aurelius') (NNP: 'Tettius') (NNPS: 'Julianus') (CC: 'and') (NNP: 'Numisius') (NNP: 'Lupus')))) (VP: (VBD: 'received') (NP: (NP: (DT: 'the') (NN: 'insignia')) (PP: (IN: 'of') (NP: (NN: 'consular') (NN: 'rank'))))))))))))))))", "10": "(ROOT: (S: (NP: (NNS: 'Vitellius')) (VP: (ADVP: (RB: 'however')) (VBD: 'lost') (NP: (NP: (NP: (DT: 'no') (NN: 'time')) (PP: (IN: 'in') (S: (VP: (VBG: 'surrendering') (NP: (PRP: 'himself')))))) (CC: 'and') (NP: (PRP$: 'his') (ADJP: (JJ: 'Guards') (PP: (TO: 'to') (NP: (DT: 'the') (NNS: 'conquerors')))) (NN: 'discretion')) (CC: 'and') (NP: (NP: (DT: 'the') (NNS: 'men')) (VP: (VBG: 'flung') (PRT: (RP: 'away')) (NP: (PRP$: 'their') (JJ: 'unlucky') (NNS: 'swords')) (PP: (ADVP: (RBR: 'more') (PP: (IN: 'in') (NP: (NN: 'anger')))) (IN: 'than') (IN: 'in') (NP: (NN: 'fear')))))))))", "11": "(ROOT: (S: (NP: (DT: 'The') (JJ: 'sole') (NN: 'cause')) (VP: (VBD: 'was') (NP: (NP: (PRP$: 'your') (JJ: 'excessive') (NN: 'loyalty')) (SBAR: (WHNP: (WDT: 'which')) (S: (NP: (PRP: 'you')) (VP: (VBD: 'displayed') (PP: (IN: 'with') (NP: (NP: (JJR: 'more') (NN: 'ardour')) (PP: (IN: 'than') (NP: (NN: 'judgement'))))))))))))", "12": "(ROOT: (FRAG: (NP: (CD: '70'))))", "13": "(ROOT: (S: (NP: (PRP: 'He')) (VP: (VBZ: 'is') (NP: (NP: (CD: 'one')) (PP: (IN: 'of') (NP: (NP: (DT: 'the') (NNS: 'characters')) (PP: (IN: 'in') (NP: (NP: (DT: 'the') (NN: 'Dialogue')) (PP: (IN: 'on') (NP: (NNP: 'Oratory') (CC: 'and') (JJ: 'many') (NNS: 'passages') (NN: 'show')))))))) (SBAR: (IN: 'that') (S: (NP: (NNP: 'Tacitus')) (VP: (VBD: 'admired') (NP: (PRP: 'him')) (ADVP: (RB: 'greatly')) (PP: (DT: 'both') (IN: 'for') (NP: (NP: (PRP$: 'his') (NN: 'character')) (CC: 'and') (NP: (PRP$: 'his') (NN: 'eloquence'))))))))))", "14": "(ROOT: (S: (NP: (NP: (DT: 'A') (NN: 'cloud')) (PP: (IN: 'of') (NP: (CD: '56')))) (VP: (VBD: 'illomened') (SBAR: (S: (S: (NP: (NNS: 'birds152')) (VP: (VBD: 'flew') (PP: (IN: 'over') (NP: (PRP$: 'his') (NN: 'head'))))) (CC: 'and') (S: (NP: (PRP$: 'its') (NN: 'density')) (VP: (VBD: 'obscured') (NP: (DT: 'the') (NN: 'daylight')))))))))", "15": "(ROOT: (S: (VP: (VBG: 'Coming') (PP: (TO: 'to') (NP: (DT: 'the') (NNS: 'Aedui128'))) (NP: (NP: (PRP: 'they')) (PP: (IN: 'in') (NP: (NP: (JJ: 'vain')) (VP: (VBN: 'sought') (NP: (DT: 'an') (NN: 'excuse')) (PP: (IN: 'for') (S: (VP: (VBG: 'fighting')))))))))))", "16": "(ROOT: (S: (NP: (NNP: 'Galba')) (VP: (VBD: 'spoke') (NP: (NP: (DT: 'these') (NNS: 'words')) (CC: 'and') (NP: (JJR: 'more'))) (PP: (TO: 'to') (NP: (NP: (DT: 'the') (JJ: 'same') (NN: 'effect')) (PP: (IN: 'in') (NP: (NP: (DT: 'the') (NN: 'tone')) (PP: (IN: 'of') (NP: (CD: 'one'))))))) (S: (VP: (VBG: 'creating') (NP: (NP: (DT: 'an') (NN: 'emperor')) (SBAR: (S: (NP: (DT: 'the') (NN: 'rest')) (VP: (VBD: 'addressed') (NP: (NNP: 'Piso')) (SBAR: (RB: 'as') (IN: 'though') (S: (NP: (PRP: 'he')) (VP: (VBD: 'were') (VP: (VBN: 'emperor') (ADVP: (RB: 'already')))))))))))))))", "17": "(ROOT: (FRAG: (NP: (CD: '96')) (VP: (VB: 'See') (NP: (NN: 'chap')))))", "18": "(ROOT: (S: (NP: (PRP: 'He')) (VP: (VBD: 'knew') (SBAR: (IN: 'that') (S: (S: (NP: (JJ: 'serious') (NNS: 'charges')) (VP: (VBD: 'had') (VP: (VBN: 'been') (VP: (VBN: 'made') (PP: (IN: 'against') (NP: (PRP: 'him'))))))) (CC: 'and') (S: (NP: (PRP$: 'his') (VBG: 'smiling') (NNS: 'congratulations')) (VP: (VBP: 'hid') (NP: (DT: 'an') (JJ: 'anxious') (NN: 'heart')))))))))", "19": "(ROOT: (NP: (NP: (CD: '135') (JJ: 'Apparently') (NNS: 'soldiers')) (NP: (NN: 'slang'))))", "20": "(ROOT: (S: (NP: (NNP: 'Fabius') (NNP: 'Valens')) (VP: (VBD: 'was') (SBAR: (SBAR: (S: (VP: (TO: 'to') (VP: (VB: 'lure') (NP: (DT: 'the') (NNPS: 'Gauls')) (PP: (TO: 'to') (NP: (PRP$: 'his') (NN: 'standard'))))))) (CC: 'or') (SBAR: (IN: 'if') (S: (NP: (PRP: 'they')) (VP: (VP: (VBD: 'refused') (S: (VP: (TO: 'to') (VP: (VP: (VB: 'devastate') (NP: (PRP$: 'their') (NN: 'country'))) (CC: 'and') (VP: (ADVP: (RB: 'then')) (VB: 'invade') (NP: (NNP: 'Italy')) (PP: (IN: 'by') (NP: (NP: (NN: 'way')) (PP: (IN: 'of') (NP: (DT: 'the') (NNP: 'Cottian'))))) (SBAR: (S: (NP: (NNP: 'Alps120') (NNP: 'Caecina')) (VP: (VBD: 'was') (S: (VP: (TO: 'to') (VP: (VB: 'follow') (NP: (DT: 'the') (JJR: 'shorter') (NN: 'route'))))))))))))) (CC: 'and') (VP: (VBD: 'descend') (PP: (IN: 'into') (NP: (NNP: 'Italy'))) (PP: (IN: 'over') (NP: (DT: 'the') (NNP: 'Pennine') (NNP: 'Pass121')))))))))))", "21": "(ROOT: (S: (NP: (NP: (PRP: 'He')) (NP: (CD: '5'))) (VP: (VBD: 'headed') (SBAR: (SBAR: (S: (NP: (DT: 'the') (NN: 'column')) (VP: (VBD: 'chose') (NP: (NP: (DT: 'the') (NN: 'campingground')) (VP: (ADVP: (RB: 'never')) (VBG: 'ceasing') (PP: (IN: 'by') (NP: (NN: 'night') (CC: 'or') (NN: 'day'))) (S: (VP: (TO: 'to') (VP: (VB: 'use') (NP: (NN: 'strategy')))))))))) (CC: 'and') (SBAR: (IN: 'if') (S: (VP: (MD: 'need') (VP: (VB: 'be') (NP: (DT: 'the') (NN: 'sword') (S: (VP: (TO: 'to') (VP: (VB: 'thwart') (NP: (DT: 'the') (NN: 'enemy'))))))))))))))", "22": "(ROOT: (PP: (IN: 'In') (NP: (NP: (DT: 'the') (NN: 'senate')) (SBAR: (S: (NP: (NP: (DT: 'the') (NNS: 'distinctions')) (VP: (VBN: 'devised') (PP: (IN: 'during') (NP: (NP: (DT: 'the') (JJ: 'long') (NNS: 'reigns')) (PP: (IN: 'of') (NP: (JJ: 'other') (NNS: 'emperors'))))))) (VP: (VBD: 'were') (RB: 'all') (VP: (VBD: 'conferred') (PP: (IN: 'on') (NP: (NNP: 'Vitellius'))) (PP: (IN: 'at') (NP: (CD: 'once338'))))))))))", "23": "(ROOT: (S: (NP: (CD: '242') (NNP: 'A') (NN: 'triumph')) (VP: (MD: 'could') (PP: (IN: 'of') (NP: (NN: 'course'))) (VP: (VB: 'be') (VP: (VBN: 'held') (ADVP: (RB: 'only')) (PP: (IN: 'for') (NP: (NP: (NNS: 'victories')) (PP: (IN: 'over') (NP: (DT: 'a') (JJ: 'foreign') (NN: 'enemy'))))))))))", "24": "(ROOT: (NP: (NNP: 'Cp')))", "25": "(ROOT: (S: (NP: (DT: 'The') (NNS: 'others')) (VP: (VBD: 'poured') (PRT: (RP: 'through')) (SBAR: (IN: 'while') (S: (S: (NP: (NP: (DT: 'the') (NNPS: 'Vitellians')) (PP: (IN: 'in') (NP: (NN: 'panic')))) (VP: (VBG: 'flung') (NP: (PRP: 'themselves')) (PRT: (RP: 'down')) (PP: (IN: 'from') (NP: (NP: (DT: 'the') (NN: 'rampart')) (CC: 'and') (NP: (NP: (DT: 'the') (JJ: 'whole') (NN: 'space')) (PP: (IN: 'between') (NP: (DT: 'the') (NN: 'camp')))))))) (CC: 'and') (S: (NP: (DT: 'the') (NNS: 'walls')) (VP: (VBD: 'became') (NP: (NP: (DT: 'a') (JJ: 'seething') (NN: 'scene')) (PP: (IN: 'of') (NP: (NN: 'carnage')))))))))))", "26": "(ROOT: (S: (NP: (DT: 'The') (JJ: 'losing') (NN: 'party') (VBG: 'being')) (VP: (ADVP: (RB: 'thus')) (VBD: 'dispersed') (PP: (IN: 'by') (NP: (JJ: 'peaceful') (NN: 'means') (NN: 'disorder'))))))", "27": "(ROOT: (S: (PP: (IN: 'Though') (ADJP: (ADJP: (RB: 'not') (JJ: 'indifferent')) (PP: (TO: 'to') (NP: (NN: 'fame'))))) (NP: (PRP: 'he')) (VP: (VBD: 'did') (RB: 'not') (VP: (VB: 'court') (NP: (PRP: 'it')) (PP: (IN: 'by') (NP: (NN: 'advertisement')))))))", "28": "(ROOT: (PP: (VBG: 'Following') (NP: (NP: (DT: 'an') (JJ: 'ancient') (NN: 'custom')) (SBAR: (S: (NP: (NP: (DT: 'the') (NN: 'tribe')) (PP: (IN: 'of') (NP: (DT: 'the') (NNPS: 'Lingones')))) (VP: (VBD: 'had') (VP: (VBN: 'made') (NP: (NP: (DT: 'a') (CD: '54') (NN: 'present')) (PP: (IN: 'of') (NP: (NP: (DT: 'a') (NN: 'pair')) (PP: (IN: 'of') (NP: (JJ: 'silver') (NNS: 'hands102')))))) (PP: (TO: 'to') (NP: (DT: 'the') (NNS: 'legions'))) (PP: (IN: 'as') (NP: (NP: (DT: 'a') (NN: 'symbol')) (PP: (IN: 'of') (NP: (NN: 'hospitality'))))))))))))", "29": "(ROOT: (NP: (NN: 'chap')))", "30": "(ROOT: (NP: (NP: (FW: 'i')) (NP: (CD: '36') (NN: 'note')) (NP: (CD: '61'))))", "31": "(ROOT: (S: (VP: (VB: 'See') (NP: (CD: 'i') (CD: '54')))))", "32": "(ROOT: (FRAG: (ADVP: (RB: 'Besides')) (SBAR: (IN: 'if') (S: (VP: (MD: 'need') (VP: (VB: 'be') (S: (NP: (PRP: 'we')) (VP: (MD: 'shall') (VP: (VB: 'have') (NP: (NP: (DT: 'the') (JJ: 'same') (NN: 'chance')) (PP: (IN: 'of') (S: (VP: (VBG: 'leaving') (ADVP: (NP: (DT: 'the') (NN: 'palace')) (RB: 'later')) (SBAR: (IN: 'if') (S: (NP: (PRP: 'we')) (VP: (VB: 'leave') (CC: 'and') (VB: 'repent') (PP: (IN: 'of') (NP: (PRP: 'it'))) (SBAR: (S: (NP: (PRP: 'it')) (VP: (MD: 'will') (RB: 'not') (VP: (VB: 'be') (PP: (IN: 'in') (NP: (PRP$: 'our') (NN: 'power') (S: (VP: (TO: 'to') (VP: (VB: 'return'))))))))))))))))))))))))))", "33": "(ROOT: (S: (NP: (NNS: 'People')) (VP: (VBD: 'began') (S: (VP: (TO: 'to') (VP: (VB: 'feel') (NP: (NN: 'pity')) (PP: (ADVP: (ADVP: (ADVP: (RB: 'not') (RB: 'perhaps')) (RB: 'so') (RB: 'much')) (PP: (IN: 'for') (NP: (NNP: 'Vitellius')))) (IN: 'as') (IN: 'for') (NP: (NP: (DT: 'the') (NN: 'throne')) (CC: 'and') (NP: (PRP$: 'its') (NNS: 'misfortunes'))))))))))"}