{"0": ["The", "road", "along", "whose", "winding", "course", "I", "have", "been", "making", "a", "delightful", "pilgrimage", "today", "has", "the", "double", "charm", "of", "natural", "beauty", "and", "of", "human", "association", "it", "is", "old", "as", "age", "is", "reckoned", "in", "this", "new", "world", "it", "has", "grown", "hard", "under", "the", "tread", "of", "sleeping", "generations", "and", "the", "great", "figures", "of", "history", "have", "passed", "over", "it", "in", "their", "journeys", "between", "the", "two", "great", "cities", "which", "mark", "its", "limits"], "1": ["Every", "new", "highway", "has", "been", "a", "new", "bond", "between", "Nature", "and", "men", "a", "new", "evidence", "of", "that", "indissoluble", "fellowship", "into", "which", "they", "are", "forever", "united"], "2": ["Who", "shall", "describe", "that", "wild", "strange", "music", "of", "the", "hermitthrush"], "3": ["ALONG", "THE", "ROADII", "V", "THE", "OPEN", "FIELDS", "VI"], "4": ["III"], "5": ["On", "the", "other", "hand", "when", "one", "lounges", "by", "the", "hour", "in", "the", "depths", "of", "the", "forest", "or", "sits", "book", "in", "hand", "under", "the", "knotted", "and", "familiar", "apple", "tree", "on", "a", "summer", "afternoon", "the", "faculty", "of", "observation", "is", "lulled", "into", "a", "dreamless", "sleep", "one", "ceases", "to", "be", "far", "enough", "away", "from", "Nature", "to", "observe", "her", "one", "becomes", "part", "of", "the", "great", "silent", "movements", "in", "the", "midst", "of", "which", "he", "sits", "mute", "and", "motionless", "while", "the", "hours", "slip", "by", "with", "the", "peace", "of", "eternity", "already", "upon", "them"], "6": ["My", "dear", "next", "week", "is", "the", "earliest", "possible", "time", "for", "our", "going"], "7": ["The", "guess", "of", "a", "great", "poetic", "mind", "has", "as", "solid", "ground", "under", "it", "as", "the", "speculation", "of", "a", "scientist", "it", "differs", "from", "the", "scientific", "theory", "only", "in", "that", "it", "is", "an", "induction", "from", "a", "greater", "number", "of", "significant", "facts"], "8": ["Meanwhile", "it", "has", "made", "the", "earth", "hospitable", "for", "us", "and", "taught", "men", "how", "to", "live", "above", "the", "brutes"], "9": ["It", "is", "among", "the", "rich", "and", "varied", "low", "colours", "of", "this", "season", "in", "wood", "and", "field", "that", "a", "true", "lover", "of", "nature", "detects", "some", "of", "her", "rarest", "touches", "of", "loveliness", "the", "low", "western", "sun", "falling", "athwart", "the", "bare", "boughs", "and", "striking", "a", "kind", "of", "subdued", "bloom", "into", "the", "brown", "hilltops", "and", "across", "the", "furze", "and", "heather", "sometimes", "reveals", "a", "hidden", "charm", "in", "the", "landscape", "which", "one", "seeks", "in", "vain", "when", "skies", "are", "softer", "and", "the", "green", "roof", "has", "been", "stretched", "over", "the", "woodland", "ways"], "10": ["The", "highway", "itself", "stands", "as", "a", "memorial", "of", "the", "most", "venerable", "customs", "and", "the", "most", "ancient", "races"], "11": ["Sometimes", "as", "I", "have", "come", "this", "way", "after", "nightfall", "I", "have", "heard", "its", "call", "across", "the", "invisible", "fields", "and", "in", "the", "sound", "I", "have", "heard", "I", "know", "not", "what", "of", "deep", "and", "joyous", "mystery", "the", "longpast", "and", "the", "faroff", "future", "whispering", "together", "under", "cover", "of", "the", "night", "of", "those", "things", "which", "the", "stars", "remember", "from", "their", "youth", "and", "to", "which", "they", "look", "forward", "in", "some", "remote", "cycle", "of", "their", "Shining"], "12": ["A", "SUMMER", "NOON", "XVIII"], "13": ["The", "next", "morning", "a", "faint", "perfume", "stole", "into", "my", "room"], "14": ["In", "castle", "and", "palace", "the", "wealth", "and", "splendour", "of", "lifeeverything", "that", "gives", "it", "grace", "and", "beauty", "to", "the", "eyeare", "treasured", "within", "massive", "walls", "and", "protected", "from", "the", "common", "gaze", "and", "touch"], "15": ["The", "bursting", "of", "the", "calyx", "announces", "the", "flower", "but", "the", "beauty", "of", "the", "perfect", "blossoming", "obliterated", "the", "very", "memory", "of", "its", "earlier", "growth"], "16": ["The", "whir", "of", "the", "locust", "high", "overhead", "by", "some", "earlier", "association", "always", "recalls", "that", "matchless", "singer", "some", "of", "whose", "notes", "Nature", "has", "never", "regained", "in", "all", "these", "later", "years"], "17": ["Unless", "you", "have", "removed", "all", "references", "to", "Project", "Gutenberg", "1E1"], "18": ["The", "people", "who", "really", "know", "me", "and", "love", "me", "seek", "me", "oftener", "at", "other", "seasons", "when", "I", "am", "more", "at", "leisure", "and", "can", "bid", "them", "to", "a", "more", "intimate", "companionship"], "19": ["we", "recalled", "to", "the", "lonely", "rooms", "the", "old", "associations", "and", "we", "quietly", "took", "up", "the", "cares", "and", "burdens", "we", "had", "dropped"], "20": ["But", "no", "cup", "of", "mans", "making", "will", "ever", "hold", "all", "that", "fountain", "has", "to", "give", "and", "to", "those", "who", "are", "really", "athirst", "these", "golden", "and", "beautifully", "wrought", "vessels", "are", "insufficient", "they", "must", "drink", "of", "the", "living", "stream"], "21": ["I", "am", "sure", "too", "that", "some", "great", "movement", "of", "life", "is", "about", "to", "display", "itself", "before", "me"], "22": ["An", "interruption", "diverts", "the", "current", "cuts", "the", "golden", "thread", "breaks", "the", "exquisite", "harmony"], "23": ["That", "which", "was", "fixed", "stable", "cast", "in", "permanent", "forms", "forever", "was", "suddenly", "annihilated", "by", "a", "revelation", "which", "spoke", "to", "the", "heart", "rather", "than", "the", "intellect", "and", "laid", "bare", "at", "a", "glance", "the", "unseen", "spiritual", "foundations", "upon", "which", "all", "things", "rest", "at", "last"], "24": ["Such", "days", "belong", "to", "the", "mountains", "and", "when", "I", "opened", "my", "window", "on", "this", "morning", "I", "was", "in", "no", "doubt", "as", "to", "the", "invitation", "held", "forth", "by", "earth", "and", "sky"], "25": ["the", "Odyssey", "in", "every", "collection", "of", "modern", "books", "for", "the", "tonic", "quality", "that", "is", "in", "it"], "26": ["Rosalind", "was", "sooner", "at", "home", "in", "this", "noble", "company", "than"], "27": ["Our", "chief", "thought", "was", "of", "the", "principle", "of", "selection", "long", "sought", "after", "by", "lovers", "of", "books", "but", "never", "yet", "found", "which", "we", "were", "certain", "would", "be", "easily", "discovered", "when", "we", "came", "to", "look", "along", "the", "shelves", "of", "the", "libraries", "in", "Arden"], "28": ["In", "a", "world", "in", "which", "all", "hearts", "beat", "true", "and", "all", "hands", "were", "helpful", "there", "would", "be", "no", "real", "hardship", "in", "Nature"], "29": ["Here", "oftenest", "come", "the", "restless", "feet", "of", "children", "and", "their", "shouts", "are", "almost", "the", "only", "sounds", "that", "ever", "break", "this", "solitude"], "30": ["It", "has", "been", "called", "an", "epical", "river", "because", "of", "the", "varied", "and", "sustained", "beauty", "through", "which", "it", "sweeps", "from", "its", "mountain", "sources", "to", "the", "sea"], "31": ["he", "knows", "not", "whence", "he", "opens", "his", "eyes", "upon", "a", "world", "which", "is", "as", "new", "to", "him", "as", "is", "the", "virgin", "continent", "to", "the", "first", "discoverer"], "32": ["I", "am", "not", "discouraged", "sooner", "or", "later", "that", "multitudinous", "rustle", "of", "the", "wild", "woods", "will", "break", "into", "clearvoiced", "speech"], "33": ["The", "light", "fell", "soft", "and", "dim", "through", "the", "thickly", "woven", "branches", "and", "among", "the", "densely", "clustered", "trunks", "underneath", "the", "deep", "masses", "of", "pine", "needles", "and", "the", "rich", "moss", "spread", "a", "carpet", "on", "which", "the", "heaviest", "footfall", "left", "the", "silence", "unbroken"], "34": ["Here", "one", "feels", "anew", "the", "eternal", "friendship", "between", "childhood", "and", "Nature", "and", "remembers", "that", "they", "only", "can", "abide", "in", "that", "fellowship", "who", "carry", "into", "riper", "years", "the", "selfforgetfulness", "the", "sweet", "unconsciousness", "the", "open", "mind", "and", "heart", "of", "a", "child"], "35": ["Hour", "after", "hour", "the", "white", "sails", "fly", "in", "mysterious", "and", "changing", "lines", "messengers", "of", "wealth", "and", "trade", "and", "pleasure", "whose", "voyages", "are", "no", "sooner", "ended", "than", "they", "begin", "again"], "36": ["Why", "should", "one", "linger", "before", "the", "picturesque", "landscape", "which", "art", "has", "imperfectly", "transferred", "to", "canvas", "when", "the", "scene", "with", "all", "its", "elusive", "play", "of", "light", "and", "shade", "lies", "outspread", "before", "him"], "37": ["On", "that", "fair", "morning", "the", "magical", "beauty", "of", "the", "world", "possessed", "us", "and", "our", "talk", "blending", "unconsciously", "with", "the", "music", "of", "the", "invisible", "choir", "was", "broken", "by", "long", "pauses"], "38": ["It", "will", "be", "so", "much", "more", "delightful", "than", "before", "suggested", "Rosalind", "because", "nobody", "will", "stare", "at", "us", "and", "we", "shall", "have", "the", "whole", "world", "to", "ourselves"]}