{"0": ["ADP", "DET", "ADJ", "NOUN", "DET", "PROPN", "ADP", "NOUN", "ADP", "DET", "PROPN", "VERB", "ADP", "PROPN", "CCONJ", "VERB", "ADJ", "NOUN", "ADP", "VERB", "NOUN", "ADP", "PROPN"], "1": ["DET", "VERB", "NOUN", "VERB", "ADV", "ADP", "DET", "NOUN", "CCONJ", "NOUN", "NOUN", "PRON", "VERB", "ADP", "NOUN", "ADP", "ADJ", "NOUN", "ADV", "ADP", "PRON", "VERB", "VERB", "ADJ", "NOUN", "CCONJ", "ADP", "PRON", "VERB", "VERB"], "2": ["PRON", "VERB", "ADV", "VERB", "ADP", "DET", "PROPN", "DET", "PROPN", "CCONJ", "PROPN", "ADV", "ADV", "VERB", "PROPN", "PROPN", "PROPN", "NOUN", "ADP", "PROPN", "CCONJ", "ADP", "PROPN"], "3": ["NUM"], "4": ["NUM", "ADP", "PROPN", "PROPN"], "5": ["DET", "ADJ", "NOUN", "ADP", "NOUN", "ADP", "DET", "ADJ", "ADJ", "NOUN", "VERB", "VERB", "ADP", "DET", "NOUN", "ADP", "ADJ", "NOUN", "CCONJ", "VERB", "DET", "NOUN", "ADP", "DET", "PROPN", "ADP", "ADJ", "NOUN", "ADP", "DET", "NOUN", "ADP", "DET", "PROPN"], "6": ["PRON", "VERB", "DET", "ADJ", "NOUN", "ADJ", "CCONJ", "VERB", "VERB", "ADP", "ADJ", "NOUN"], "7": ["DET", "NOUN", "VERB", "VERB", "ADP", "DET", "NOUN", "PART", "VERB", "VERB", "VERB", "ADP", "DET", "NOUN", "ADP", "DET", "NOUN", "ADP", "DET", "PROPN", "ADP", "DET", "ADJ", "NOUN", "ADP", "DET", "NOUN", "PROPN", "CCONJ", "DET", "NOUN", "ADP", "PROPN", "PROPN", "ADP", "DET", "NOUN", "ADP", "PROPN", "NUM", "CCONJ", "ADP", "DET", "ADJ", "NOUN", "NUM"], "8": ["NUM"], "9": ["PROPN", "ADV", "VERB", "PRON", "ADP", "NOUN", "ADP", "ADJ", "NOUN", "ADP", "DET", "NOUN", "ADP", "ADJ", "NOUN", "CCONJ", "ADP", "DET", "NOUN", "ADV", "VERB", "ADJ", "NOUN"], "10": ["ADP", "DET", "NOUN", "ADP", "ADJ", "NOUN", "ADJ", "VERB", "VERB", "ADJ", "ADP", "VERB", "ADV", "VERB", "DET", "NOUN", "ADP", "PROPN", "PART", "VERB", "ADP", "NOUN", "ADV", "ADJ", "NOUN", "ADP", "PROPN", "PROPN", "PROPN", "CCONJ", "PROPN", "VERB", "ADP", "DET", "NOUN", "CCONJ", "NOUN", "ADP", "ADJ", "NOUN", "NUM", "ADV", "ADJ", "NOUN", "ADP", "ADJ", "NOUN", "ADP", "ADJ", "NOUN", "VERB", "CCONJ", "VERB", "NOUN", "ADP", "DET", "ADJ", "NOUN", "VERB", "VERB", "ADV", "ADP", "DET", "NOUN", "ADP", "DET", "NOUN", "CCONJ", "DET", "NOUN", "ADP", "DET", "VERB", "NOUN", "NUM", "CCONJ", "ADP", "DET", "NOUN", "ADP", "DET", "NOUN", "CCONJ", "DET", "NOUN", "ADP", "ADJ", "NOUN"], "11": ["NUM"], "12": ["ADP", "DET", "NOUN", "DET", "PROPN", "VERB", "VERB", "ADP", "DET", "NOUN", "ADP", "DET", "PROPN", "CCONJ", "DET", "NOUN", "ADP", "DET", "PROPN", "ADP", "DET", "NOUN"], "13": ["NUM"], "14": ["CCONJ", "DET", "VERB", "ADP", "NOUN", "ADJ", "NOUN", "NOUN", "ADP", "PROPN"], "15": ["CCONJ", "PUNCT", "NUM", "ADP", "PROPN", "ADP", "VERB", "ADV", "ADV", "VERB", "ADP", "DET", "PROPN", "ADP", "PROPN"], "16": ["ADP", "DET", "ADJ", "NOUN", "ADP", "PROPN", "ADJ", "ADP", "DET", "NOUN", "VERB", "DET", "PROPN"], "17": ["NUM"], "18": ["PRON", "VERB"], "19": ["DET", "ADJ", "NOUN", "ADP", "DET", "ADJ", "NOUN", "NUM", "VERB", "ADJ", "NOUN", "ADP", "DET", "PROPN", "CCONJ", "ADJ", "NOUN", "VERB", "ADV", "ADV", "ADP", "DET", "NOUN", "ADP", "DET", "PROPN"], "20": ["ADJ", "NOUN", "VERB", "ADV", "DET", "NOUN", "ADP", "ADJ", "NOUN"], "21": ["DET", "ADJ", "ADP", "PRON", "VERB", "ADV", "DET", "NOUN", "NOUN", "NUM", "DET", "NOUN", "ADP", "NOUN", "ADP", "DET", "NOUN", "ADP", "DET", "NOUN", "ADP", "NOUN", "ADP", "PRON", "VERB", "VERB", "PRON", "ADP", "DET", "NOUN", "ADP", "DET", "NOUN"], "22": ["PROPN", "VERB", "PROPN", "NOUN", "ADJ", "ADP", "DET", "NOUN", "ADP", "DET", "PROPN"], "23": ["DET", "NOUN", "DET", "ADJ", "NOUN", "ADP", "NOUN", "CCONJ", "NOUN", "ADP", "DET", "PROPN", "VERB", "VERB", "ADP", "NOUN", "CCONJ", "ADP", "DET", "NOUN", "CCONJ", "NOUN", "ADP", "DET", "NOUN"], "24": ["NUM"], "25": ["ADJ", "NOUN", "VERB", "NOUN", "VERB", "VERB", "ADP", "PROPN", "CCONJ", "PROPN"], "26": ["DET", "PROPN", "VERB", "ADP", "ADJ", "NOUN", "CCONJ", "ADJ", "NOUN", "NUM", "ADP", "NOUN", "CCONJ", "NOUN", "VERB", "CCONJ", "VERB", "PART", "ADJ", "NOUN", "NOUN", "CCONJ", "ADP", "DET", "ADJ", "NOUN", "VERB", "PART", "DET", "NOUN", "ADP", "ADJ", "ADJ"], "27": ["ADJ", "VERB", "ADJ", "PRON", "VERB", "DET", "NOUN", "ADP", "DET", "NOUN", "ADP", "PROPN", "ADP", "DET", "ADJ", "NOUN"], "28": ["NOUN"], "29": ["DET", "NOUN", "ADP", "DET", "NOUN", "NOUN", "ADP", "DET", "PROPN"], "30": ["NUM"], "31": ["ADV", "ADJ", "NOUN", "ADP", "DET", "PROPN", "ADP", "PROPN", "VERB", "PROPN", "NOUN", "ADP", "ADJ", "NUM", "NOUN"]}